<?xml version="1.0" encoding="UTF-8"?>
<QCARConfig xmlns:xsi="http://www.w3.org/2001/XMLSchema-instance" xsi:noNamespaceSchemaLocation="qcar_config.xsd">
  <Tracking>
    <ImageTarget name="Lampisterie_mire" size="0.400000 0.319501" />
    <ImageTarget name="Grisoumetre_mire" size="0.200000 0.200000" />
    <ImageTarget name="Genephone_Mire" size="0.200000 0.200000" />
    <ImageTarget name="Chaussures_mire" size="0.200000 0.310777" />
    <ImageTarget name="Bricquet_Mire" size="0.200000 0.199667" />
    <ImageTarget name="48388061_2245671689010251_4239631190761406464_n" size="5.000000 5.000000" />
  </Tracking>
</QCARConfig>
